{"type":"FeatureCollection","crs":{"type":"name","properties":{"name":"EPSG:4326"}},"features":[{"type":"Feature","geometry":{"type":"Point","coordinates":[130.989156,32.293963]},"properties":{"id":111009100,"name":"小川内川（鶴井手橋）","name_kana":"","ofc_cd":89,"sys_id":1,"sys_cam_id":"11009100","pause":0,"date_type":2,"cam_kind":4,"own_cd":11009}},{"type":"Feature","geometry":{"type":"Point","coordinates":[131.056981,32.322757]},"properties":{"id":111009123,"name":"湯山川（登山橋）","name_kana":"","ofc_cd":89,"sys_id":1,"sys_cam_id":"11009123","pause":0,"date_type":2,"cam_kind":4,"own_cd":11009}},{"type":"Feature","geometry":{"type":"Point","coordinates":[130.98035,32.288407]},"properties":{"id":122829072,"name":"球磨川８８ｋ６００鵜木橋下流","name_kana":"","ofc_cd":89,"sys_id":1,"sys_cam_id":"22829072","pause":0,"date_type":2,"cam_kind":4,"own_cd":22829}}]}