{"type":"FeatureCollection","crs":{"type":"name","properties":{"name":"EPSG:4326"}},"features":[{"type":"Feature","geometry":{"type":"Point","coordinates":[137.325,34.828611111]},"properties":{"id":105889009,"name":"国府","name_kana":"","ofc_cd":85,"sys_id":1,"sys_cam_id":"5889009","pause":0,"date_type":0,"cam_kind":4,"own_cd":5889}},{"type":"Feature","geometry":{"type":"Point","coordinates":[137.387777778,34.835]},"properties":{"id":105889010,"name":"佐土","name_kana":"","ofc_cd":85,"sys_id":1,"sys_cam_id":"5889010","pause":0,"date_type":0,"cam_kind":4,"own_cd":5889}},{"type":"Feature","geometry":{"type":"Point","coordinates":[137.434837,34.858862]},"properties":{"id":121781046,"name":"豊川　21k000　右岸","name_kana":"","ofc_cd":85,"sys_id":1,"sys_cam_id":"21781046","pause":0,"date_type":2,"cam_kind":4,"own_cd":21781}},{"type":"Feature","geometry":{"type":"Point","coordinates":[137.458914,34.872138]},"properties":{"id":121781047,"name":"豊川　23k400　右岸","name_kana":"","ofc_cd":85,"sys_id":1,"sys_cam_id":"21781047","pause":0,"date_type":2,"cam_kind":4,"own_cd":21781}},{"type":"Feature","geometry":{"type":"Point","coordinates":[137.377532,34.794225]},"properties":{"id":121781050,"name":"豊川放水路　4k200　左岸","name_kana":"","ofc_cd":85,"sys_id":1,"sys_cam_id":"21781050","pause":0,"date_type":2,"cam_kind":4,"own_cd":21781}},{"type":"Feature","geometry":{"type":"Point","coordinates":[137.361851,34.79061]},"properties":{"id":121781053,"name":"豊川放水路　2k800　右岸","name_kana":"","ofc_cd":85,"sys_id":1,"sys_cam_id":"21781053","pause":0,"date_type":2,"cam_kind":4,"own_cd":21781}},{"type":"Feature","geometry":{"type":"Point","coordinates":[137.368161,34.792618]},"properties":{"id":121781054,"name":"豊川放水路　3k400　右岸","name_kana":"","ofc_cd":85,"sys_id":1,"sys_cam_id":"21781054","pause":0,"date_type":2,"cam_kind":4,"own_cd":21781}},{"type":"Feature","geometry":{"type":"Point","coordinates":[137.436835,34.820056]},"properties":{"id":121781056,"name":"間川　0k200　左岸","name_kana":"","ofc_cd":85,"sys_id":1,"sys_cam_id":"21781056","pause":0,"date_type":2,"cam_kind":4,"own_cd":21781}},{"type":"Feature","geometry":{"type":"Point","coordinates":[137.437099,34.820866]},"properties":{"id":121781064,"name":"間川　0k200　右岸","name_kana":"","ofc_cd":85,"sys_id":1,"sys_cam_id":"21781064","pause":0,"date_type":1,"cam_kind":4,"own_cd":21781}},{"type":"Feature","geometry":{"type":"Point","coordinates":[137.440836,34.849813]},"properties":{"id":121781066,"name":"豊川　19k800　左岸　金沢霞付近","name_kana":"","ofc_cd":85,"sys_id":1,"sys_cam_id":"21781066","pause":0,"date_type":1,"cam_kind":4,"own_cd":21781}},{"type":"Feature","geometry":{"type":"Point","coordinates":[137.4564833,34.8716667]},"properties":{"id":221781024,"name":"清水川樋門付近","name_kana":"","ofc_cd":85,"sys_id":2,"sys_cam_id":"21781009","pause":0,"date_type":0,"cam_kind":2,"own_cd":21781}},{"type":"Feature","geometry":{"type":"Point","coordinates":[137.4515222,34.8708472]},"properties":{"id":221781025,"name":"シャラ川樋管付近","name_kana":"","ofc_cd":85,"sys_id":2,"sys_cam_id":"21781010","pause":0,"date_type":0,"cam_kind":2,"own_cd":21781}},{"type":"Feature","geometry":{"type":"Point","coordinates":[137.4461417,34.8660972]},"properties":{"id":221781026,"name":"江島橋付近","name_kana":"","ofc_cd":85,"sys_id":2,"sys_cam_id":"21781011","pause":0,"date_type":0,"cam_kind":2,"own_cd":21781}},{"type":"Feature","geometry":{"type":"Point","coordinates":[137.4408056,34.8497639]},"properties":{"id":221781027,"name":"金沢霞付近","name_kana":"","ofc_cd":85,"sys_id":2,"sys_cam_id":"21781012","pause":0,"date_type":0,"cam_kind":2,"own_cd":21781}},{"type":"Feature","geometry":{"type":"Point","coordinates":[137.4221111,34.8389278]},"properties":{"id":221781028,"name":"東名豊川橋付近","name_kana":"","ofc_cd":85,"sys_id":2,"sys_cam_id":"21781013","pause":0,"date_type":0,"cam_kind":2,"own_cd":21781}},{"type":"Feature","geometry":{"type":"Point","coordinates":[137.4292111,34.8248611]},"properties":{"id":221781029,"name":"二葉樋門付近","name_kana":"","ofc_cd":85,"sys_id":2,"sys_cam_id":"21781014","pause":0,"date_type":0,"cam_kind":2,"own_cd":21781}},{"type":"Feature","geometry":{"type":"Point","coordinates":[137.4347944,34.8214944]},"properties":{"id":221781030,"name":"賀茂霞付近","name_kana":"","ofc_cd":85,"sys_id":2,"sys_cam_id":"21781015","pause":0,"date_type":0,"cam_kind":2,"own_cd":21781}},{"type":"Feature","geometry":{"type":"Point","coordinates":[137.4303639,34.818875]},"properties":{"id":221781031,"name":"三上橋付近","name_kana":"","ofc_cd":85,"sys_id":2,"sys_cam_id":"21781016","pause":0,"date_type":0,"cam_kind":2,"own_cd":21781}},{"type":"Feature","geometry":{"type":"Point","coordinates":[137.4173194,34.8100389]},"properties":{"id":221781032,"name":"当古橋付近","name_kana":"","ofc_cd":85,"sys_id":2,"sys_cam_id":"21781017","pause":0,"date_type":0,"cam_kind":2,"own_cd":21781}},{"type":"Feature","geometry":{"type":"Point","coordinates":[137.4016889,34.8055167]},"properties":{"id":221781033,"name":"古川排水機場 屋上付近","name_kana":"","ofc_cd":85,"sys_id":2,"sys_cam_id":"21781018","pause":0,"date_type":0,"cam_kind":2,"own_cd":21781}},{"type":"Feature","geometry":{"type":"Point","coordinates":[137.4005861,34.8042278]},"properties":{"id":221781034,"name":"放水路上流付近","name_kana":"","ofc_cd":85,"sys_id":2,"sys_cam_id":"21781033","pause":0,"date_type":0,"cam_kind":2,"own_cd":21781}},{"type":"Feature","geometry":{"type":"Point","coordinates":[137.3987917,34.8017444]},"properties":{"id":221781035,"name":"放水路下流付近","name_kana":"","ofc_cd":85,"sys_id":2,"sys_cam_id":"21781034","pause":0,"date_type":0,"cam_kind":2,"own_cd":21781}},{"type":"Feature","geometry":{"type":"Point","coordinates":[137.3893444,34.7994556]},"properties":{"id":221781036,"name":"正岡付近","name_kana":"","ofc_cd":85,"sys_id":2,"sys_cam_id":"21781035","pause":0,"date_type":0,"cam_kind":2,"own_cd":21781}},{"type":"Feature","geometry":{"type":"Point","coordinates":[137.3825472,34.7957472]},"properties":{"id":221781037,"name":"篠束橋付近","name_kana":"","ofc_cd":85,"sys_id":2,"sys_cam_id":"21781036","pause":0,"date_type":0,"cam_kind":2,"own_cd":21781}},{"type":"Feature","geometry":{"type":"Point","coordinates":[137.3651056,34.7919278]},"properties":{"id":221781038,"name":"小坂井排水機場付近","name_kana":"","ofc_cd":85,"sys_id":2,"sys_cam_id":"21781037","pause":0,"date_type":0,"cam_kind":2,"own_cd":21781}},{"type":"Feature","geometry":{"type":"Point","coordinates":[137.44165,34.8491694]},"properties":{"id":221781067,"name":"金沢霞堤内","name_kana":"","ofc_cd":85,"sys_id":2,"sys_cam_id":"21781030","pause":0,"date_type":0,"cam_kind":2,"own_cd":21781}},{"type":"Feature","geometry":{"type":"Point","coordinates":[137.4355528,34.8171417]},"properties":{"id":221781068,"name":"権現山","name_kana":"","ofc_cd":85,"sys_id":2,"sys_cam_id":"21781031","pause":0,"date_type":0,"cam_kind":2,"own_cd":21781}},{"type":"Feature","geometry":{"type":"Point","coordinates":[137.3658028,34.790375]},"properties":{"id":221781069,"name":"JR飯田線","name_kana":"","ofc_cd":85,"sys_id":2,"sys_cam_id":"21781042","pause":0,"date_type":0,"cam_kind":2,"own_cd":21781}},{"type":"Feature","geometry":{"type":"Point","coordinates":[137.402352778,34.797772222]},"properties":{"id":221781081,"name":"下条橋右岸下流付近","name_kana":"","ofc_cd":85,"sys_id":2,"sys_cam_id":"21781081","pause":0,"date_type":0,"cam_kind":2,"own_cd":21781}},{"type":"Feature","geometry":{"type":"Point","coordinates":[137.437052778,34.852811111]},"properties":{"id":221781083,"name":"金沢橋付近","name_kana":"","ofc_cd":85,"sys_id":2,"sys_cam_id":"21781083","pause":0,"date_type":0,"cam_kind":2,"own_cd":21781}}]}