{"type":"FeatureCollection","crs":{"type":"name","properties":{"name":"EPSG:4326"}},"features":[{"type":"Feature","geometry":{"type":"Point","coordinates":[134.548791666,34.092383333]},"properties":{"id":222549010,"name":"吉野川 右 5ｋ0徳島市 新町樋門","name_kana":"","ofc_cd":88,"sys_id":2,"sys_cam_id":"22549014","pause":0,"date_type":0,"cam_kind":2,"own_cd":22549}},{"type":"Feature","geometry":{"type":"Point","coordinates":[134.596833333,34.072830555]},"properties":{"id":222549016,"name":"吉野川 右 0ｋ0徳島市 河口","name_kana":"","ofc_cd":88,"sys_id":2,"sys_cam_id":"22549020","pause":0,"date_type":0,"cam_kind":2,"own_cd":22549}},{"type":"Feature","geometry":{"type":"Point","coordinates":[134.555227777,34.089305555]},"properties":{"id":222549017,"name":"吉野川 右 4ｋ4徳島市 徳島事務所","name_kana":"","ofc_cd":88,"sys_id":2,"sys_cam_id":"22549025","pause":0,"date_type":0,"cam_kind":2,"own_cd":22549}},{"type":"Feature","geometry":{"type":"Point","coordinates":[134.529444,34.133333]},"properties":{"id":122549008,"name":"JR橋箇所　旧吉野川右岸12ｋ4付近","name_kana":"","ofc_cd":88,"sys_id":1,"sys_cam_id":"22549008","pause":0,"date_type":2,"cam_kind":4,"own_cd":22549}},{"type":"Feature","geometry":{"type":"Point","coordinates":[134.543333,34.14]},"properties":{"id":122549010,"name":"共栄橋箇所　旧吉野川左岸9ｋ4付近","name_kana":"","ofc_cd":88,"sys_id":1,"sys_cam_id":"22549010","pause":0,"date_type":2,"cam_kind":4,"own_cd":22549}},{"type":"Feature","geometry":{"type":"Point","coordinates":[134.588889,34.150833]},"properties":{"id":122549014,"name":"大津箇所　旧吉野川左岸2ｋ8付近","name_kana":"","ofc_cd":88,"sys_id":1,"sys_cam_id":"22549014","pause":0,"date_type":2,"cam_kind":4,"own_cd":22549}},{"type":"Feature","geometry":{"type":"Point","coordinates":[134.5771555,33.9430092]},"properties":{"id":122551001,"name":"持井","name_kana":"","ofc_cd":88,"sys_id":1,"sys_cam_id":"22551001","pause":0,"date_type":2,"cam_kind":4,"own_cd":22551}},{"type":"Feature","geometry":{"type":"Point","coordinates":[134.5611458,33.9230763]},"properties":{"id":122551002,"name":"加茂谷橋","name_kana":"","ofc_cd":88,"sys_id":1,"sys_cam_id":"22551002","pause":0,"date_type":2,"cam_kind":4,"own_cd":22551}},{"type":"Feature","geometry":{"type":"Point","coordinates":[134.5489623,33.9131378]},"properties":{"id":122551003,"name":"東加茂","name_kana":"","ofc_cd":88,"sys_id":1,"sys_cam_id":"22551003","pause":0,"date_type":2,"cam_kind":4,"own_cd":22551}},{"type":"Feature","geometry":{"type":"Point","coordinates":[134.5455787,33.911452]},"properties":{"id":122551004,"name":"西加茂","name_kana":"","ofc_cd":88,"sys_id":1,"sys_cam_id":"22551004","pause":0,"date_type":2,"cam_kind":4,"own_cd":22551}},{"type":"Feature","geometry":{"type":"Point","coordinates":[134.548521,33.915436]},"properties":{"id":122551005,"name":"東加茂（堤防天端）","name_kana":"","ofc_cd":88,"sys_id":1,"sys_cam_id":"22551005","pause":0,"date_type":2,"cam_kind":4,"own_cd":22551}},{"type":"Feature","geometry":{"type":"Point","coordinates":[134.545336,33.915201]},"properties":{"id":122551006,"name":"西加茂（堤防天端）","name_kana":"","ofc_cd":88,"sys_id":1,"sys_cam_id":"22551006","pause":0,"date_type":2,"cam_kind":4,"own_cd":22551}},{"type":"Feature","geometry":{"type":"Point","coordinates":[134.566901,33.928804]},"properties":{"id":122551007,"name":"楠根下流","name_kana":"","ofc_cd":88,"sys_id":1,"sys_cam_id":"22551007","pause":0,"date_type":2,"cam_kind":4,"own_cd":22551}},{"type":"Feature","geometry":{"type":"Point","coordinates":[134.547546,33.919269]},"properties":{"id":122551008,"name":"深瀬","name_kana":"","ofc_cd":88,"sys_id":1,"sys_cam_id":"22551008","pause":0,"date_type":2,"cam_kind":4,"own_cd":22551}},{"type":"Feature","geometry":{"type":"Point","coordinates":[134.635579,33.914362]},"properties":{"id":122551009,"name":"オワタ","name_kana":"","ofc_cd":88,"sys_id":1,"sys_cam_id":"22551009","pause":0,"date_type":2,"cam_kind":4,"own_cd":22551}},{"type":"Feature","geometry":{"type":"Point","coordinates":[134.631902,33.911653]},"properties":{"id":122551010,"name":"会下","name_kana":"","ofc_cd":88,"sys_id":1,"sys_cam_id":"22551010","pause":0,"date_type":2,"cam_kind":4,"own_cd":22551}},{"type":"Feature","geometry":{"type":"Point","coordinates":[134.626687,33.904289]},"properties":{"id":122551011,"name":"石合","name_kana":"","ofc_cd":88,"sys_id":1,"sys_cam_id":"22551011","pause":0,"date_type":2,"cam_kind":4,"own_cd":22551}},{"type":"Feature","geometry":{"type":"Point","coordinates":[134.701166666,33.938286111]},"properties":{"id":222551001,"name":"那賀川 右 -0ｋ8阿南市 河口","name_kana":"","ofc_cd":88,"sys_id":2,"sys_cam_id":"22551004","pause":0,"date_type":0,"cam_kind":2,"own_cd":22551}},{"type":"Feature","geometry":{"type":"Point","coordinates":[134.621863888,33.937638888]},"properties":{"id":222551002,"name":"那賀川 右 7ｋ0阿南市 那賀川橋","name_kana":"","ofc_cd":88,"sys_id":2,"sys_cam_id":"22551005","pause":0,"date_type":0,"cam_kind":2,"own_cd":22551}},{"type":"Feature","geometry":{"type":"Point","coordinates":[134.703530555,33.932236111]},"properties":{"id":222551003,"name":"桑野川 左 -0ｋ5 阿南市 河口","name_kana":"","ofc_cd":88,"sys_id":2,"sys_cam_id":"22551006","pause":0,"date_type":0,"cam_kind":2,"own_cd":22551}},{"type":"Feature","geometry":{"type":"Point","coordinates":[134.618947222,33.906227777]},"properties":{"id":222551004,"name":"桑野川 左 9ｋ1阿南市 長生橋","name_kana":"","ofc_cd":88,"sys_id":2,"sys_cam_id":"22551007","pause":0,"date_type":0,"cam_kind":2,"own_cd":22551}},{"type":"Feature","geometry":{"type":"Point","coordinates":[134.550277777,33.917777777]},"properties":{"id":222551005,"name":"那賀川 右 16ｋ5 阿南市 加茂谷","name_kana":"","ofc_cd":88,"sys_id":2,"sys_cam_id":"22551008","pause":0,"date_type":0,"cam_kind":2,"own_cd":22551}},{"type":"Feature","geometry":{"type":"Point","coordinates":[134.625369444,33.906538888]},"properties":{"id":222551006,"name":"桑野川 左 8ｋ5 阿南市 津乃峰橋","name_kana":"","ofc_cd":88,"sys_id":2,"sys_cam_id":"22551009","pause":0,"date_type":0,"cam_kind":2,"own_cd":22551}},{"type":"Feature","geometry":{"type":"Point","coordinates":[134.5559,33.923822222]},"properties":{"id":222551007,"name":"那賀川 右 15ｋ5 阿南市 吉井上流","name_kana":"","ofc_cd":88,"sys_id":2,"sys_cam_id":"22551010","pause":0,"date_type":0,"cam_kind":2,"own_cd":22551}},{"type":"Feature","geometry":{"type":"Point","coordinates":[134.666388888,33.924441666]},"properties":{"id":222551008,"name":"桑野川 右 3ｋ6阿南市 事務所","name_kana":"","ofc_cd":88,"sys_id":2,"sys_cam_id":"22551011","pause":0,"date_type":0,"cam_kind":2,"own_cd":22551}},{"type":"Feature","geometry":{"type":"Point","coordinates":[134.222509,34.062486]},"properties":{"id":122549007,"name":"川田箇所　吉野川右岸37ｋ4付近","name_kana":"","ofc_cd":88,"sys_id":1,"sys_cam_id":"22549007","pause":0,"date_type":2,"cam_kind":4,"own_cd":22549}},{"type":"Feature","geometry":{"type":"Point","coordinates":[134.237955555,34.067005555]},"properties":{"id":222549015,"name":"吉野川 右 36ｋ0吉野川市 瀬詰大橋","name_kana":"","ofc_cd":88,"sys_id":2,"sys_cam_id":"22549019","pause":0,"date_type":0,"cam_kind":2,"own_cd":22549}},{"type":"Feature","geometry":{"type":"Point","coordinates":[134.267044444,34.065491666]},"properties":{"id":222549020,"name":"吉野川 右 33ｋ1吉野川市 ほたる川樋門","name_kana":"","ofc_cd":88,"sys_id":2,"sys_cam_id":"22549041","pause":0,"date_type":0,"cam_kind":2,"own_cd":22549}},{"type":"Feature","geometry":{"type":"Point","coordinates":[134.197775,34.062775]},"properties":{"id":222549001,"name":"吉野川右40ｋ0吉野川市岩津橋","name_kana":"","ofc_cd":88,"sys_id":2,"sys_cam_id":"22549001","pause":0,"date_type":0,"cam_kind":2,"own_cd":22549}},{"type":"Feature","geometry":{"type":"Point","coordinates":[134.371691666,34.090941666]},"properties":{"id":222549004,"name":"吉野川 左 23ｋ0阿波市 柿原堰下流","name_kana":"","ofc_cd":88,"sys_id":2,"sys_cam_id":"22549008","pause":0,"date_type":0,"cam_kind":2,"own_cd":22549}},{"type":"Feature","geometry":{"type":"Point","coordinates":[134.351766666,34.083397222]},"properties":{"id":222549019,"name":"吉野川 右 25ｋ0吉野川市 阿波中央橋","name_kana":"","ofc_cd":88,"sys_id":2,"sys_cam_id":"22549036","pause":0,"date_type":0,"cam_kind":2,"own_cd":22549}},{"type":"Feature","geometry":{"type":"Point","coordinates":[134.153611,34.058889]},"properties":{"id":122549005,"name":"明連川樋門箇所　吉野川右岸44ｋ0付近","name_kana":"","ofc_cd":88,"sys_id":1,"sys_cam_id":"22549005","pause":0,"date_type":2,"cam_kind":4,"own_cd":22549}},{"type":"Feature","geometry":{"type":"Point","coordinates":[134.1744528,34.0550417]},"properties":{"id":122549006,"name":"穴吹川左岸箇所　吉野川右岸42ｋ2付近","name_kana":"","ofc_cd":88,"sys_id":1,"sys_cam_id":"22549006","pause":0,"date_type":2,"cam_kind":4,"own_cd":22549}},{"type":"Feature","geometry":{"type":"Point","coordinates":[134.056194444,34.047363888]},"properties":{"id":222549021,"name":"吉野川 左 53ｋ8美馬市 美馬橋","name_kana":"","ofc_cd":88,"sys_id":2,"sys_cam_id":"22549042","pause":0,"date_type":0,"cam_kind":2,"own_cd":22549}},{"type":"Feature","geometry":{"type":"Point","coordinates":[133.844997222,34.032775]},"properties":{"id":222549002,"name":"吉野川右74ｋ9三好市池田観測所","name_kana":"","ofc_cd":88,"sys_id":2,"sys_cam_id":"22549002","pause":0,"date_type":0,"cam_kind":2,"own_cd":22549}},{"type":"Feature","geometry":{"type":"Point","coordinates":[134.438605555,34.101627777]},"properties":{"id":222549005,"name":"吉野川 右 16ｋ3石井町 六条大橋","name_kana":"","ofc_cd":88,"sys_id":2,"sys_cam_id":"22549009","pause":0,"date_type":0,"cam_kind":2,"own_cd":22549}},{"type":"Feature","geometry":{"type":"Point","coordinates":[134.565833,34.146111]},"properties":{"id":122549011,"name":"長岸橋右岸箇所　旧吉野川右岸6ｋ6付近","name_kana":"","ofc_cd":88,"sys_id":1,"sys_cam_id":"22549011","pause":0,"date_type":2,"cam_kind":4,"own_cd":22549}},{"type":"Feature","geometry":{"type":"Point","coordinates":[134.566944,34.146944]},"properties":{"id":122549012,"name":"長岸橋左岸箇所　旧吉野川左岸6ｋ4付近","name_kana":"","ofc_cd":88,"sys_id":1,"sys_cam_id":"22549012","pause":0,"date_type":2,"cam_kind":4,"own_cd":22549}},{"type":"Feature","geometry":{"type":"Point","coordinates":[134.581389,34.139444]},"properties":{"id":122549013,"name":"中喜来箇所　旧吉野川左岸4ｋ2付近","name_kana":"","ofc_cd":88,"sys_id":1,"sys_cam_id":"22549013","pause":0,"date_type":2,"cam_kind":4,"own_cd":22549}},{"type":"Feature","geometry":{"type":"Point","coordinates":[134.617405555,34.140291666]},"properties":{"id":222549012,"name":"旧吉野川 右 0ｋ松茂町 河口","name_kana":"","ofc_cd":88,"sys_id":2,"sys_cam_id":"22549016","pause":0,"date_type":0,"cam_kind":2,"own_cd":22549}},{"type":"Feature","geometry":{"type":"Point","coordinates":[134.543194,34.12895]},"properties":{"id":122549009,"name":"新高橋箇所　旧吉野川左岸10ｋ8付近","name_kana":"","ofc_cd":88,"sys_id":1,"sys_cam_id":"22549009","pause":0,"date_type":2,"cam_kind":4,"own_cd":22549}},{"type":"Feature","geometry":{"type":"Point","coordinates":[134.552691666,34.109733333]},"properties":{"id":222549008,"name":"今切川 左 8ｋ5北島町 今切川河口堰上流","name_kana":"いまぎれがわ　ひだり　８ｋ５　きたじまちょう　いまぎれがわかこうぜきじょうりゅう","ofc_cd":88,"sys_id":2,"sys_cam_id":"22549012","pause":0,"date_type":0,"cam_kind":2,"own_cd":22549}},{"type":"Feature","geometry":{"type":"Point","coordinates":[134.469163888,34.14]},"properties":{"id":222549003,"name":"旧吉野川左18ｋ6板野町大寺橋","name_kana":"","ofc_cd":88,"sys_id":2,"sys_cam_id":"22549003","pause":0,"date_type":0,"cam_kind":2,"own_cd":22549}},{"type":"Feature","geometry":{"type":"Point","coordinates":[134.458491666,34.113763888]},"properties":{"id":222549006,"name":"吉野川 左 14ｋ1上板町 第十堰","name_kana":"","ofc_cd":88,"sys_id":2,"sys_cam_id":"22549010","pause":0,"date_type":0,"cam_kind":2,"own_cd":22549}},{"type":"Feature","geometry":{"type":"Point","coordinates":[134.444763888,34.108338888]},"properties":{"id":222549007,"name":"吉野川 左 15ｋ6上板町 第十樋門","name_kana":"","ofc_cd":88,"sys_id":2,"sys_cam_id":"22549011","pause":0,"date_type":0,"cam_kind":2,"own_cd":22549}},{"type":"Feature","geometry":{"type":"Point","coordinates":[134.457458333,34.106663888]},"properties":{"id":222549018,"name":"吉野川 右 14ｋ6徳島市 第十堰下流","name_kana":"","ofc_cd":88,"sys_id":2,"sys_cam_id":"22549029","pause":0,"date_type":0,"cam_kind":2,"own_cd":22549}},{"type":"Feature","geometry":{"type":"Point","coordinates":[134.448430555,34.109816666]},"properties":{"id":222549022,"name":"旧吉野川 右 23ｋ8上板町 第十樋門","name_kana":"","ofc_cd":88,"sys_id":2,"sys_cam_id":"22549050","pause":0,"date_type":0,"cam_kind":2,"own_cd":22549}},{"type":"Feature","geometry":{"type":"Point","coordinates":[134.056389,34.042778]},"properties":{"id":122549004,"name":"貞光箇所　吉野川右岸53ｋ8付近","name_kana":"","ofc_cd":88,"sys_id":1,"sys_cam_id":"22549004","pause":0,"date_type":2,"cam_kind":4,"own_cd":22549}},{"type":"Feature","geometry":{"type":"Point","coordinates":[134.064591666,34.043916666]},"properties":{"id":222549009,"name":"吉野川 右 53ｋ0つるぎ町 貞光川左岸","name_kana":"","ofc_cd":88,"sys_id":2,"sys_cam_id":"22549013","pause":0,"date_type":0,"cam_kind":2,"own_cd":22549}},{"type":"Feature","geometry":{"type":"Point","coordinates":[133.930947,34.047295]},"properties":{"id":122549001,"name":"加茂第二箇所　吉野川右岸65ｋ8付近","name_kana":"","ofc_cd":88,"sys_id":1,"sys_cam_id":"22549001","pause":0,"date_type":2,"cam_kind":4,"own_cd":22549}},{"type":"Feature","geometry":{"type":"Point","coordinates":[133.936667,34.041111]},"properties":{"id":122549002,"name":"加茂谷橋箇所　吉野川右岸65ｋ0付近","name_kana":"","ofc_cd":88,"sys_id":1,"sys_cam_id":"22549002","pause":0,"date_type":2,"cam_kind":4,"own_cd":22549}},{"type":"Feature","geometry":{"type":"Point","coordinates":[133.966111,34.035]},"properties":{"id":122549003,"name":"山口谷川左岸　吉野川右岸62ｋ2付近","name_kana":"","ofc_cd":88,"sys_id":1,"sys_cam_id":"22549003","pause":0,"date_type":2,"cam_kind":4,"own_cd":22549}},{"type":"Feature","geometry":{"type":"Point","coordinates":[133.969605555,34.036966666]},"properties":{"id":222549011,"name":"吉野川 右 62Ｋ0東みよし町 山口谷","name_kana":"","ofc_cd":88,"sys_id":2,"sys_cam_id":"22549015","pause":0,"date_type":0,"cam_kind":2,"own_cd":22549}}]}