{"type":"FeatureCollection","crs":{"type":"name","properties":{"name":"EPSG:4326"}},"features":[{"type":"Feature","geometry":{"type":"Point","coordinates":[140.401459,37.517642]},"properties":{"id":101793047,"name":"安達太良川（ふれあい橋）","name_kana":"あだたらがわ（ふれあいはし）","ofc_cd":82,"sys_id":1,"sys_cam_id":"1793047","pause":0,"date_type":2,"cam_kind":4,"own_cd":1793}},{"type":"Feature","geometry":{"type":"Point","coordinates":[140.399265,37.482993]},"properties":{"id":101793048,"name":"五百川（五百川橋）","name_kana":"ごひゃくがわ（ごひゃくがわはし）","ofc_cd":82,"sys_id":1,"sys_cam_id":"1793048","pause":0,"date_type":2,"cam_kind":4,"own_cd":1793}},{"type":"Feature","geometry":{"type":"Point","coordinates":[140.403251,37.52405]},"properties":{"id":101793049,"name":"百日川（枝沢橋）","name_kana":"ひゃくにちがわ（えださわはし）","ofc_cd":82,"sys_id":1,"sys_cam_id":"1793049","pause":0,"date_type":2,"cam_kind":4,"own_cd":1793}},{"type":"Feature","geometry":{"type":"Point","coordinates":[140.4364876,37.5085043]},"properties":{"id":101793112,"name":"仲川（小田部橋）","name_kana":"なかがわ（こたべはし）","ofc_cd":82,"sys_id":1,"sys_cam_id":"1793112","pause":0,"date_type":2,"cam_kind":4,"own_cd":1793}},{"type":"Feature","geometry":{"type":"Point","coordinates":[140.4017917,37.4993533]},"properties":{"id":101793194,"name":"瀬戸川（山田橋）","name_kana":"せとがわ（やまだばし）","ofc_cd":82,"sys_id":1,"sys_cam_id":"1793194","pause":0,"date_type":1,"cam_kind":4,"own_cd":1793}},{"type":"Feature","geometry":{"type":"Point","coordinates":[140.6153394,37.8477265]},"properties":{"id":101793291,"name":"広瀬川 (孫老内橋)","name_kana":"","ofc_cd":82,"sys_id":1,"sys_cam_id":"1793291","pause":0,"date_type":1,"cam_kind":4,"own_cd":1793}},{"type":"Feature","geometry":{"type":"Point","coordinates":[140.424506,37.542708]},"properties":{"id":121063272,"name":"和田北大沢(阿R64.2k+80)","name_kana":"わだきたおおさわ","ofc_cd":82,"sys_id":1,"sys_cam_id":"21063272","pause":0,"date_type":2,"cam_kind":4,"own_cd":21063}},{"type":"Feature","geometry":{"type":"Point","coordinates":[140.405321,37.503514]},"properties":{"id":121063279,"name":"糠沢赤木(阿R69.8k)","name_kana":"ぬかざわあかぎ","ofc_cd":82,"sys_id":1,"sys_cam_id":"21063279","pause":0,"date_type":2,"cam_kind":4,"own_cd":21063}},{"type":"Feature","geometry":{"type":"Point","coordinates":[140.404347,37.516275]},"properties":{"id":121063330,"name":"本宮下町(阿L68.3k)","name_kana":"もとみやしもまち","ofc_cd":82,"sys_id":1,"sys_cam_id":"21063330","pause":0,"date_type":2,"cam_kind":4,"own_cd":21063}},{"type":"Feature","geometry":{"type":"Point","coordinates":[140.4125,37.519444]},"properties":{"id":221063028,"name":"高木樋管","name_kana":"たかぎひかん","ofc_cd":82,"sys_id":2,"sys_cam_id":"21063061","pause":0,"date_type":0,"cam_kind":2,"own_cd":21063}},{"type":"Feature","geometry":{"type":"Point","coordinates":[140.406944,37.516389]},"properties":{"id":221063029,"name":"昭代橋上流","name_kana":"しょうだいばしじょうりゅう","ofc_cd":82,"sys_id":2,"sys_cam_id":"21063060","pause":0,"date_type":0,"cam_kind":2,"own_cd":21063}},{"type":"Feature","geometry":{"type":"Point","coordinates":[140.406389,37.515278]},"properties":{"id":221063030,"name":"本宮水位観測所","name_kana":"もとみやすいいかんそくじょ","ofc_cd":82,"sys_id":2,"sys_cam_id":"21063073","pause":0,"date_type":0,"cam_kind":2,"own_cd":21063}},{"type":"Feature","geometry":{"type":"Point","coordinates":[140.403333,37.511389]},"properties":{"id":221063031,"name":"安達橋上流","name_kana":"あだちばしじょうりゅう","ofc_cd":82,"sys_id":2,"sys_cam_id":"21063059","pause":0,"date_type":0,"cam_kind":2,"own_cd":21063}}]}