{"type":"FeatureCollection","crs":{"type":"name","properties":{"name":"EPSG:4326"}},"features":[{"type":"Feature","geometry":{"type":"Point","coordinates":[139.24457,36.116891]},"properties":{"id":121280123,"name":"埼玉県寄居町赤浜　荒川右岸　89.8kp","name_kana":"","ofc_cd":83,"sys_id":1,"sys_cam_id":"21280123","pause":0,"date_type":2,"cam_kind":4,"own_cd":21280}},{"type":"Feature","geometry":{"type":"Point","coordinates":[139.1994417,36.1116639]},"properties":{"id":221280022,"name":"寄居水位観測所","name_kana":"","ofc_cd":83,"sys_id":2,"sys_cam_id":"11010065","pause":0,"date_type":0,"cam_kind":2,"own_cd":21280}}]}