{"type":"FeatureCollection","crs":{"type":"name","properties":{"name":"EPSG:4326"}},"features":[{"type":"Feature","geometry":{"type":"Point","coordinates":[140.743893333,42.904444444]},"properties":{"id":100257228,"name":"倶登山川  2.4Kp","name_kana":"","ofc_cd":81,"sys_id":1,"sys_cam_id":"257228","pause":0,"date_type":2,"cam_kind":4,"own_cd":257}},{"type":"Feature","geometry":{"type":"Point","coordinates":[140.752998,42.885713]},"properties":{"id":100257238,"name":"尻別川  37.2Kp","name_kana":"","ofc_cd":81,"sys_id":1,"sys_cam_id":"257238","pause":0,"date_type":2,"cam_kind":4,"own_cd":257}}]}