{"type":"FeatureCollection","crs":{"type":"name","properties":{"name":"EPSG:4326"}},"features":[{"type":"Feature","geometry":{"type":"Point","coordinates":[140.513333,37.961667]},"properties":{"id":221039001,"name":"管理所屋上","name_kana":"","ofc_cd":82,"sys_id":2,"sys_cam_id":"21039003","pause":0,"date_type":0,"cam_kind":2,"own_cd":21039}},{"type":"Feature","geometry":{"type":"Point","coordinates":[140.516389,37.961111]},"properties":{"id":221039002,"name":"ダム左岸","name_kana":"","ofc_cd":82,"sys_id":2,"sys_cam_id":"21039001","pause":0,"date_type":0,"cam_kind":2,"own_cd":21039}},{"type":"Feature","geometry":{"type":"Point","coordinates":[140.510278,37.958333]},"properties":{"id":221039003,"name":"ダム上流右岸","name_kana":"","ofc_cd":82,"sys_id":2,"sys_cam_id":"21039002","pause":0,"date_type":0,"cam_kind":2,"own_cd":21039}},{"type":"Feature","geometry":{"type":"Point","coordinates":[140.473333,37.979167]},"properties":{"id":221039006,"name":"七ヶ宿公園","name_kana":"","ofc_cd":82,"sys_id":2,"sys_cam_id":"21039006","pause":0,"date_type":0,"cam_kind":2,"own_cd":21039}}]}