{"type":"FeatureCollection","crs":{"type":"name","properties":{"name":"EPSG:4326"}},"features":[{"type":"Feature","geometry":{"type":"Point","coordinates":[131.2055556,33.2733333]},"properties":{"id":111265044,"name":"竜門橋","name_kana":"","ofc_cd":89,"sys_id":1,"sys_cam_id":"11265044","pause":0,"date_type":2,"cam_kind":4,"own_cd":11265}},{"type":"Feature","geometry":{"type":"Point","coordinates":[131.1547222,33.1930556]},"properties":{"id":111265045,"name":"第一桐木橋","name_kana":"","ofc_cd":89,"sys_id":1,"sys_cam_id":"11265045","pause":0,"date_type":2,"cam_kind":4,"own_cd":11265}},{"type":"Feature","geometry":{"type":"Point","coordinates":[131.2111111,33.2272222]},"properties":{"id":111265046,"name":"寺田橋","name_kana":"","ofc_cd":89,"sys_id":1,"sys_cam_id":"11265046","pause":0,"date_type":2,"cam_kind":4,"own_cd":11265}},{"type":"Feature","geometry":{"type":"Point","coordinates":[131.2068889,33.2048056]},"properties":{"id":111265106,"name":"界橋","name_kana":"","ofc_cd":89,"sys_id":1,"sys_cam_id":"11265106","pause":0,"date_type":2,"cam_kind":4,"own_cd":11265}},{"type":"Feature","geometry":{"type":"Point","coordinates":[131.1754444,33.2207222]},"properties":{"id":111265109,"name":"佃橋","name_kana":"","ofc_cd":89,"sys_id":1,"sys_cam_id":"11265109","pause":0,"date_type":2,"cam_kind":4,"own_cd":11265}},{"type":"Feature","geometry":{"type":"Point","coordinates":[131.2660556,33.2221944]},"properties":{"id":111265110,"name":"滝上第三橋","name_kana":"","ofc_cd":89,"sys_id":1,"sys_cam_id":"11265110","pause":0,"date_type":2,"cam_kind":4,"own_cd":11265}},{"type":"Feature","geometry":{"type":"Point","coordinates":[131.1756667,33.25625]},"properties":{"id":111265111,"name":"団子橋","name_kana":"","ofc_cd":89,"sys_id":1,"sys_cam_id":"11265111","pause":0,"date_type":2,"cam_kind":4,"own_cd":11265}},{"type":"Feature","geometry":{"type":"Point","coordinates":[131.171173,33.2131322]},"properties":{"id":111265112,"name":"柚之木橋","name_kana":"","ofc_cd":89,"sys_id":1,"sys_cam_id":"11265112","pause":0,"date_type":2,"cam_kind":4,"own_cd":11265}},{"type":"Feature","geometry":{"type":"Point","coordinates":[131.1628333,33.1831389]},"properties":{"id":111265113,"name":"梶屋橋","name_kana":"","ofc_cd":89,"sys_id":1,"sys_cam_id":"11265113","pause":0,"date_type":2,"cam_kind":4,"own_cd":11265}},{"type":"Feature","geometry":{"type":"Point","coordinates":[131.2538632,33.1578245]},"properties":{"id":111265114,"name":"大川橋","name_kana":"","ofc_cd":89,"sys_id":1,"sys_cam_id":"11265114","pause":0,"date_type":2,"cam_kind":4,"own_cd":11265}}]}