{"type":"FeatureCollection","crs":{"type":"name","properties":{"name":"EPSG:4326"}},"features":[{"type":"Feature","geometry":{"type":"Point","coordinates":[139.1251694,35.3347361]},"properties":{"id":103585051,"name":"吉田島","name_kana":"","ofc_cd":83,"sys_id":1,"sys_cam_id":"3585051","pause":0,"date_type":2,"cam_kind":4,"own_cd":3585}},{"type":"Feature","geometry":{"type":"Point","coordinates":[139.134791,35.333733]},"properties":{"id":103585074,"name":"酒匂川 足柄大橋","name_kana":"","ofc_cd":83,"sys_id":1,"sys_cam_id":"3585074","pause":0,"date_type":2,"cam_kind":4,"own_cd":3585}},{"type":"Feature","geometry":{"type":"Point","coordinates":[139.13333333,35.32283333]},"properties":{"id":103585103,"name":"仙了川　下中丸橋","name_kana":"","ofc_cd":83,"sys_id":1,"sys_cam_id":"3585103","pause":0,"date_type":2,"cam_kind":4,"own_cd":3585}}]}