{"type":"FeatureCollection","crs":{"type":"name","properties":{"name":"EPSG:4326"}},"features":[{"type":"Feature","geometry":{"type":"Point","coordinates":[130.53,31.6130556]},"properties":{"id":311777001,"name":"岩崎橋","name_kana":"","ofc_cd":46,"sys_id":3,"sys_cam_id":"46010037","pause":0,"date_type":1,"cam_kind":2,"own_cd":11777}},{"type":"Feature","geometry":{"type":"Point","coordinates":[130.4663861,31.6875]},"properties":{"id":311777002,"name":"宮山橋","name_kana":"","ofc_cd":46,"sys_id":3,"sys_cam_id":"46010038","pause":0,"date_type":1,"cam_kind":2,"own_cd":11777}},{"type":"Feature","geometry":{"type":"Point","coordinates":[130.5641639,31.6083333]},"properties":{"id":311777003,"name":"一ツ橋","name_kana":"","ofc_cd":46,"sys_id":3,"sys_cam_id":"46010039","pause":0,"date_type":1,"cam_kind":2,"own_cd":11777}},{"type":"Feature","geometry":{"type":"Point","coordinates":[130.5297222,31.5763889]},"properties":{"id":311777004,"name":"田上橋","name_kana":"","ofc_cd":46,"sys_id":3,"sys_cam_id":"46010040","pause":0,"date_type":1,"cam_kind":2,"own_cd":11777}},{"type":"Feature","geometry":{"type":"Point","coordinates":[130.5,31.5461111]},"properties":{"id":311777005,"name":"宮下橋","name_kana":"","ofc_cd":46,"sys_id":3,"sys_cam_id":"46010041","pause":0,"date_type":1,"cam_kind":2,"own_cd":11777}},{"type":"Feature","geometry":{"type":"Point","coordinates":[130.909346,31.359638]},"properties":{"id":122858132,"name":"肝属川左岸10k9（流合橋下流）","name_kana":"","ofc_cd":89,"sys_id":1,"sys_cam_id":"22858132","pause":0,"date_type":2,"cam_kind":4,"own_cd":22858}},{"type":"Feature","geometry":{"type":"Point","coordinates":[130.883454,31.364941]},"properties":{"id":122858133,"name":"肝属川左岸14k2（大正橋下流）","name_kana":"","ofc_cd":89,"sys_id":1,"sys_cam_id":"22858133","pause":0,"date_type":2,"cam_kind":4,"own_cd":22858}},{"type":"Feature","geometry":{"type":"Point","coordinates":[130.871434,31.370704]},"properties":{"id":122858134,"name":"肝属川左岸15k6（新川田崎大橋下流）","name_kana":"","ofc_cd":89,"sys_id":1,"sys_cam_id":"22858134","pause":0,"date_type":2,"cam_kind":4,"own_cd":22858}},{"type":"Feature","geometry":{"type":"Point","coordinates":[130.85376,31.390523]},"properties":{"id":122858135,"name":"肝属川左岸19k2（鹿屋小前）","name_kana":"","ofc_cd":89,"sys_id":1,"sys_cam_id":"22858135","pause":0,"date_type":2,"cam_kind":4,"own_cd":22858}},{"type":"Feature","geometry":{"type":"Point","coordinates":[130.848591,31.418062]},"properties":{"id":122858136,"name":"肝属川右岸23k6（大園橋下流）","name_kana":"","ofc_cd":89,"sys_id":1,"sys_cam_id":"22858136","pause":0,"date_type":2,"cam_kind":4,"own_cd":22858}},{"type":"Feature","geometry":{"type":"Point","coordinates":[130.942827,31.441439]},"properties":{"id":122858137,"name":"串良川左岸10k3（下中橋）","name_kana":"","ofc_cd":89,"sys_id":1,"sys_cam_id":"22858137","pause":0,"date_type":2,"cam_kind":4,"own_cd":22858}},{"type":"Feature","geometry":{"type":"Point","coordinates":[130.90091,31.330882]},"properties":{"id":122858139,"name":"姶良川左岸3k1（更生橋上流）","name_kana":"","ofc_cd":89,"sys_id":1,"sys_cam_id":"22858139","pause":0,"date_type":2,"cam_kind":4,"own_cd":22858}},{"type":"Feature","geometry":{"type":"Point","coordinates":[130.855830555,31.3975]},"properties":{"id":222858001,"name":"王子橋水位","name_kana":"","ofc_cd":89,"sys_id":2,"sys_cam_id":"46010011","pause":0,"date_type":0,"cam_kind":2,"own_cd":22858}},{"type":"Feature","geometry":{"type":"Point","coordinates":[130.899166666,31.324719444]},"properties":{"id":222858002,"name":"月見橋","name_kana":"","ofc_cd":89,"sys_id":2,"sys_cam_id":"46010012","pause":0,"date_type":0,"cam_kind":2,"own_cd":22858}},{"type":"Feature","geometry":{"type":"Point","coordinates":[130.849997222,31.376666666]},"properties":{"id":222858003,"name":"鉄道橋水位","name_kana":"","ofc_cd":89,"sys_id":2,"sys_cam_id":"46010013","pause":0,"date_type":0,"cam_kind":2,"own_cd":22858}},{"type":"Feature","geometry":{"type":"Point","coordinates":[130.851941666,31.383611111]},"properties":{"id":222858004,"name":"朝日橋水位","name_kana":"","ofc_cd":89,"sys_id":2,"sys_cam_id":"46010014","pause":0,"date_type":0,"cam_kind":2,"own_cd":22858}},{"type":"Feature","geometry":{"type":"Point","coordinates":[130.902222222,31.343608333]},"properties":{"id":222858005,"name":"姶良橋水位","name_kana":"","ofc_cd":89,"sys_id":2,"sys_cam_id":"46010015","pause":0,"date_type":0,"cam_kind":2,"own_cd":22858}},{"type":"Feature","geometry":{"type":"Point","coordinates":[130.950830555,31.436802777]},"properties":{"id":222858014,"name":"霧島大橋","name_kana":"","ofc_cd":89,"sys_id":2,"sys_cam_id":"46010024","pause":0,"date_type":0,"cam_kind":2,"own_cd":22858}},{"type":"Feature","geometry":{"type":"Point","coordinates":[130.960830555,31.391386111]},"properties":{"id":222858018,"name":"豊栄水位","name_kana":"","ofc_cd":89,"sys_id":2,"sys_cam_id":"46010028","pause":0,"date_type":0,"cam_kind":2,"own_cd":22858}},{"type":"Feature","geometry":{"type":"Point","coordinates":[130.958377777,31.400138888]},"properties":{"id":222858021,"name":"大塚原","name_kana":"","ofc_cd":89,"sys_id":2,"sys_cam_id":"46010031","pause":0,"date_type":0,"cam_kind":2,"own_cd":22858}},{"type":"Feature","geometry":{"type":"Point","coordinates":[130.897358333,31.355647222]},"properties":{"id":222858022,"name":"川北","name_kana":"","ofc_cd":89,"sys_id":2,"sys_cam_id":"46010032","pause":0,"date_type":0,"cam_kind":2,"own_cd":22858}},{"type":"Feature","geometry":{"type":"Point","coordinates":[130.851805555,31.389719444]},"properties":{"id":222858023,"name":"大手町","name_kana":"","ofc_cd":89,"sys_id":2,"sys_cam_id":"46010033","pause":0,"date_type":0,"cam_kind":2,"own_cd":22858}},{"type":"Feature","geometry":{"type":"Point","coordinates":[130.905,31.353333333]},"properties":{"id":222858024,"name":"下名","name_kana":"","ofc_cd":89,"sys_id":2,"sys_cam_id":"46010034","pause":0,"date_type":0,"cam_kind":2,"own_cd":22858}},{"type":"Feature","geometry":{"type":"Point","coordinates":[130.9025,31.318238888]},"properties":{"id":222858025,"name":"中福良","name_kana":"","ofc_cd":89,"sys_id":2,"sys_cam_id":"46010035","pause":0,"date_type":0,"cam_kind":2,"own_cd":22858}},{"type":"Feature","geometry":{"type":"Point","coordinates":[130.903377777,31.308794444]},"properties":{"id":222858026,"name":"上名","name_kana":"","ofc_cd":89,"sys_id":2,"sys_cam_id":"46010036","pause":0,"date_type":0,"cam_kind":2,"own_cd":22858}},{"type":"Feature","geometry":{"type":"Point","coordinates":[130.3519417,32.0875]},"properties":{"id":311777011,"name":"春日橋","name_kana":"","ofc_cd":46,"sys_id":3,"sys_cam_id":"46010047","pause":0,"date_type":1,"cam_kind":2,"own_cd":11777}},{"type":"Feature","geometry":{"type":"Point","coordinates":[130.583897,32.014253]},"properties":{"id":122856116,"name":"川内川 64k400 筏場樋門","name_kana":"","ofc_cd":89,"sys_id":1,"sys_cam_id":"22856116","pause":0,"date_type":0,"cam_kind":4,"own_cd":22856}},{"type":"Feature","geometry":{"type":"Point","coordinates":[130.597704,32.011966]},"properties":{"id":122856117,"name":"川内川 66k200 曽木第一樋門","name_kana":"","ofc_cd":89,"sys_id":1,"sys_cam_id":"22856117","pause":0,"date_type":0,"cam_kind":4,"own_cd":22856}},{"type":"Feature","geometry":{"type":"Point","coordinates":[130.674433,31.97853]},"properties":{"id":122856118,"name":"川内川 81k000 広田第一樋門","name_kana":"","ofc_cd":89,"sys_id":1,"sys_cam_id":"22856118","pause":0,"date_type":0,"cam_kind":4,"own_cd":22856}},{"type":"Feature","geometry":{"type":"Point","coordinates":[130.610773,32.037678]},"properties":{"id":122856130,"name":"羽月川   4k000 金波田第三樋門","name_kana":"","ofc_cd":89,"sys_id":1,"sys_cam_id":"22856130","pause":0,"date_type":0,"cam_kind":4,"own_cd":22856}},{"type":"Feature","geometry":{"type":"Point","coordinates":[130.628747222,32.005925]},"properties":{"id":222856010,"name":"荒田天神橋","name_kana":"","ofc_cd":89,"sys_id":2,"sys_cam_id":"46010008","pause":0,"date_type":0,"cam_kind":2,"own_cd":22856}},{"type":"Feature","geometry":{"type":"Point","coordinates":[130.576111111,32.009722222]},"properties":{"id":222856011,"name":"曽木の滝","name_kana":"","ofc_cd":89,"sys_id":2,"sys_cam_id":"46010009","pause":0,"date_type":0,"cam_kind":2,"own_cd":22856}},{"type":"Feature","geometry":{"type":"Point","coordinates":[130.603888888,32.052869444]},"properties":{"id":222856012,"name":"羽月橋","name_kana":"","ofc_cd":89,"sys_id":2,"sys_cam_id":"46010010","pause":0,"date_type":0,"cam_kind":2,"own_cd":22856}},{"type":"Feature","geometry":{"type":"Point","coordinates":[130.223291,31.830977]},"properties":{"id":122856110,"name":"川内川   3k200 倉浦排水樋門","name_kana":"","ofc_cd":89,"sys_id":1,"sys_cam_id":"22856110","pause":0,"date_type":0,"cam_kind":4,"own_cd":22856}},{"type":"Feature","geometry":{"type":"Point","coordinates":[130.358403,31.848495]},"properties":{"id":122856111,"name":"川内川 21k200 庄込第一樋門","name_kana":"","ofc_cd":89,"sys_id":1,"sys_cam_id":"22856111","pause":0,"date_type":0,"cam_kind":4,"own_cd":22856}},{"type":"Feature","geometry":{"type":"Point","coordinates":[130.400145,31.854073]},"properties":{"id":122856112,"name":"川内川 28k200 倉野第二樋管","name_kana":"","ofc_cd":89,"sys_id":1,"sys_cam_id":"22856112","pause":0,"date_type":0,"cam_kind":4,"own_cd":22856}},{"type":"Feature","geometry":{"type":"Point","coordinates":[130.308886,31.806907]},"properties":{"id":122856144,"name":"隈之城川1k800　日暮樋門","name_kana":"","ofc_cd":89,"sys_id":1,"sys_cam_id":"22856144","pause":0,"date_type":0,"cam_kind":4,"own_cd":22856}},{"type":"Feature","geometry":{"type":"Point","coordinates":[130.438965,31.797287]},"properties":{"id":14601215001,"name":"大宮井堰","name_kana":"おおみやいぜき","ofc_cd":89,"sys_id":1,"sys_cam_id":"4601215001","pause":0,"date_type":2,"cam_kind":4,"own_cd":4601215}},{"type":"Feature","geometry":{"type":"Point","coordinates":[130.440638,31.789297]},"properties":{"id":14601215002,"name":"鹿子田橋","name_kana":"かのこだばし","ofc_cd":89,"sys_id":1,"sys_cam_id":"4601215002","pause":0,"date_type":2,"cam_kind":4,"own_cd":4601215}},{"type":"Feature","geometry":{"type":"Point","coordinates":[130.456429,31.771473]},"properties":{"id":14601215003,"name":"黒武者橋","name_kana":"くろむしゃばし","ofc_cd":89,"sys_id":1,"sys_cam_id":"4601215003","pause":0,"date_type":2,"cam_kind":4,"own_cd":4601215}},{"type":"Feature","geometry":{"type":"Point","coordinates":[130.310833333,31.820461111]},"properties":{"id":222856003,"name":"太平橋","name_kana":"","ofc_cd":89,"sys_id":2,"sys_cam_id":"46010001","pause":0,"date_type":0,"cam_kind":2,"own_cd":22856}},{"type":"Feature","geometry":{"type":"Point","coordinates":[130.335833333,31.862636111]},"properties":{"id":222856007,"name":"東郷橋","name_kana":"","ofc_cd":89,"sys_id":2,"sys_cam_id":"46010005","pause":0,"date_type":0,"cam_kind":2,"own_cd":22856}},{"type":"Feature","geometry":{"type":"Point","coordinates":[130.390969444,31.856711111]},"properties":{"id":222856008,"name":"倉野橋","name_kana":"","ofc_cd":89,"sys_id":2,"sys_cam_id":"46010006","pause":0,"date_type":0,"cam_kind":2,"own_cd":22856}},{"type":"Feature","geometry":{"type":"Point","coordinates":[130.3241639,31.8083333]},"properties":{"id":311777010,"name":"草原橋","name_kana":"","ofc_cd":46,"sys_id":3,"sys_cam_id":"46010046","pause":0,"date_type":1,"cam_kind":2,"own_cd":11777}},{"type":"Feature","geometry":{"type":"Point","coordinates":[130.3941639,31.6305556]},"properties":{"id":311777006,"name":"荒瀬橋","name_kana":"","ofc_cd":46,"sys_id":3,"sys_cam_id":"46010042","pause":0,"date_type":1,"cam_kind":2,"own_cd":11777}},{"type":"Feature","geometry":{"type":"Point","coordinates":[130.7547222,31.7705528]},"properties":{"id":311777012,"name":"日当山橋","name_kana":"","ofc_cd":46,"sys_id":3,"sys_cam_id":"46010048","pause":0,"date_type":1,"cam_kind":2,"own_cd":11777}},{"type":"Feature","geometry":{"type":"Point","coordinates":[130.3269444,31.4277778]},"properties":{"id":311777008,"name":"万之瀬橋","name_kana":"","ofc_cd":46,"sys_id":3,"sys_cam_id":"46010044","pause":0,"date_type":1,"cam_kind":2,"own_cd":11777}},{"type":"Feature","geometry":{"type":"Point","coordinates":[130.3161111,31.4091639]},"properties":{"id":311777009,"name":"日新橋","name_kana":"","ofc_cd":46,"sys_id":3,"sys_cam_id":"46010045","pause":0,"date_type":1,"cam_kind":2,"own_cd":11777}},{"type":"Feature","geometry":{"type":"Point","coordinates":[130.3802778,31.3805556]},"properties":{"id":311777007,"name":"大渡橋","name_kana":"","ofc_cd":46,"sys_id":3,"sys_cam_id":"46010043","pause":0,"date_type":1,"cam_kind":2,"own_cd":11777}},{"type":"Feature","geometry":{"type":"Point","coordinates":[130.42839,31.866973]},"properties":{"id":122856113,"name":"川内川 31k900 運床川樋門","name_kana":"","ofc_cd":89,"sys_id":1,"sys_cam_id":"22856113","pause":0,"date_type":0,"cam_kind":4,"own_cd":22856}},{"type":"Feature","geometry":{"type":"Point","coordinates":[130.464944,31.925754]},"properties":{"id":122856114,"name":"川内川 39k800 夜星川","name_kana":"","ofc_cd":89,"sys_id":1,"sys_cam_id":"22856114","pause":0,"date_type":0,"cam_kind":4,"own_cd":22856}},{"type":"Feature","geometry":{"type":"Point","coordinates":[130.480293,31.956762]},"properties":{"id":122856115,"name":"川内川 45k200 神子橋","name_kana":"","ofc_cd":89,"sys_id":1,"sys_cam_id":"22856115","pause":0,"date_type":0,"cam_kind":4,"own_cd":22856}},{"type":"Feature","geometry":{"type":"Point","coordinates":[130.455830555,31.907775]},"properties":{"id":222856006,"name":"宮之城","name_kana":"","ofc_cd":89,"sys_id":2,"sys_cam_id":"46010004","pause":0,"date_type":0,"cam_kind":2,"own_cd":22856}},{"type":"Feature","geometry":{"type":"Point","coordinates":[130.466386111,31.935461111]},"properties":{"id":222856009,"name":"柏原橋","name_kana":"","ofc_cd":89,"sys_id":2,"sys_cam_id":"46010007","pause":0,"date_type":0,"cam_kind":2,"own_cd":22856}},{"type":"Feature","geometry":{"type":"Point","coordinates":[130.687769,31.97156]},"properties":{"id":122856119,"name":"川内川 82k800 広田川樋門","name_kana":"","ofc_cd":89,"sys_id":1,"sys_cam_id":"22856119","pause":0,"date_type":0,"cam_kind":4,"own_cd":22856}},{"type":"Feature","geometry":{"type":"Point","coordinates":[130.68922,31.964791]},"properties":{"id":122856120,"name":"川内川 83k600 轟橋","name_kana":"","ofc_cd":89,"sys_id":1,"sys_cam_id":"22856120","pause":0,"date_type":0,"cam_kind":4,"own_cd":22856}},{"type":"Feature","geometry":{"type":"Point","coordinates":[130.704001,31.959683]},"properties":{"id":122856121,"name":"川内川 85k000 田尾原第一樋門","name_kana":"","ofc_cd":89,"sys_id":1,"sys_cam_id":"22856121","pause":0,"date_type":0,"cam_kind":4,"own_cd":22856}},{"type":"Feature","geometry":{"type":"Point","coordinates":[130.707964,31.947347]},"properties":{"id":122856122,"name":"川内川 87k000 綿打川第一樋門","name_kana":"","ofc_cd":89,"sys_id":1,"sys_cam_id":"22856122","pause":0,"date_type":0,"cam_kind":4,"own_cd":22856}},{"type":"Feature","geometry":{"type":"Point","coordinates":[130.74097,32.00137]},"properties":{"id":122856123,"name":"川内川 95k000 宇都川樋門","name_kana":"","ofc_cd":89,"sys_id":1,"sys_cam_id":"22856123","pause":0,"date_type":0,"cam_kind":4,"own_cd":22856}},{"type":"Feature","geometry":{"type":"Point","coordinates":[130.741455,32.026473]},"properties":{"id":122856124,"name":"川内川 97k800 中鶴橋","name_kana":"","ofc_cd":89,"sys_id":1,"sys_cam_id":"22856124","pause":0,"date_type":0,"cam_kind":4,"own_cd":22856}},{"type":"Feature","geometry":{"type":"Point","coordinates":[130.738648,32.028812]},"properties":{"id":122856125,"name":"川内川 98k200 鶴丸水門","name_kana":"","ofc_cd":89,"sys_id":1,"sys_cam_id":"22856125","pause":0,"date_type":0,"cam_kind":4,"own_cd":22856}},{"type":"Feature","geometry":{"type":"Point","coordinates":[130.743609,32.03614]},"properties":{"id":122856126,"name":"川内川 99k200 鶴丸用排水樋門","name_kana":"","ofc_cd":89,"sys_id":1,"sys_cam_id":"22856126","pause":0,"date_type":0,"cam_kind":4,"own_cd":22856}},{"type":"Feature","geometry":{"type":"Point","coordinates":[130.719675,31.953980555]},"properties":{"id":222856004,"name":"栗野橋","name_kana":"","ofc_cd":89,"sys_id":2,"sys_cam_id":"46010002","pause":0,"date_type":0,"cam_kind":2,"own_cd":22856}},{"type":"Feature","geometry":{"type":"Point","coordinates":[130.747080555,32.013608333]},"properties":{"id":222856005,"name":"吉松橋","name_kana":"","ofc_cd":89,"sys_id":2,"sys_cam_id":"46010003","pause":0,"date_type":0,"cam_kind":2,"own_cd":22856}},{"type":"Feature","geometry":{"type":"Point","coordinates":[130.959997222,31.388330555]},"properties":{"id":222858007,"name":"岡崎","name_kana":"","ofc_cd":89,"sys_id":2,"sys_cam_id":"46010017","pause":0,"date_type":0,"cam_kind":2,"own_cd":22858}},{"type":"Feature","geometry":{"type":"Point","coordinates":[130.953425,31.420091666]},"properties":{"id":222858013,"name":"十五社橋","name_kana":"","ofc_cd":89,"sys_id":2,"sys_cam_id":"46010023","pause":0,"date_type":0,"cam_kind":2,"own_cd":22858}},{"type":"Feature","geometry":{"type":"Point","coordinates":[130.974258333,31.3606]},"properties":{"id":222858015,"name":"俣瀬橋水位","name_kana":"","ofc_cd":89,"sys_id":2,"sys_cam_id":"46010025","pause":0,"date_type":0,"cam_kind":2,"own_cd":22858}},{"type":"Feature","geometry":{"type":"Point","coordinates":[131.000275,31.358516666]},"properties":{"id":222858019,"name":"新川西","name_kana":"","ofc_cd":89,"sys_id":2,"sys_cam_id":"46010029","pause":0,"date_type":0,"cam_kind":2,"own_cd":22858}},{"type":"Feature","geometry":{"type":"Point","coordinates":[130.95778,31.363655]},"properties":{"id":122858131,"name":"肝属川右岸5k8（高山川合流部）","name_kana":"","ofc_cd":89,"sys_id":1,"sys_cam_id":"22858131","pause":0,"date_type":2,"cam_kind":4,"own_cd":22858}},{"type":"Feature","geometry":{"type":"Point","coordinates":[130.947037,31.326609]},"properties":{"id":122858138,"name":"高山川左岸5k000","name_kana":"","ofc_cd":89,"sys_id":1,"sys_cam_id":"22858138","pause":0,"date_type":2,"cam_kind":4,"own_cd":22858}},{"type":"Feature","geometry":{"type":"Point","coordinates":[130.955830555,31.358055555]},"properties":{"id":222858006,"name":"下之門","name_kana":"","ofc_cd":89,"sys_id":2,"sys_cam_id":"46010016","pause":0,"date_type":0,"cam_kind":2,"own_cd":22858}},{"type":"Feature","geometry":{"type":"Point","coordinates":[130.993886111,31.354444444]},"properties":{"id":222858008,"name":"波見","name_kana":"","ofc_cd":89,"sys_id":2,"sys_cam_id":"46010018","pause":0,"date_type":0,"cam_kind":2,"own_cd":22858}},{"type":"Feature","geometry":{"type":"Point","coordinates":[130.975555555,31.358888888]},"properties":{"id":222858009,"name":"俣瀬橋","name_kana":"","ofc_cd":89,"sys_id":2,"sys_cam_id":"46010019","pause":0,"date_type":0,"cam_kind":2,"own_cd":22858}},{"type":"Feature","geometry":{"type":"Point","coordinates":[130.940830555,31.336944444]},"properties":{"id":222858010,"name":"神之市","name_kana":"","ofc_cd":89,"sys_id":2,"sys_cam_id":"46010020","pause":0,"date_type":0,"cam_kind":2,"own_cd":22858}},{"type":"Feature","geometry":{"type":"Point","coordinates":[131.012497222,31.356388888]},"properties":{"id":222858011,"name":"河口","name_kana":"","ofc_cd":89,"sys_id":2,"sys_cam_id":"46010021","pause":0,"date_type":0,"cam_kind":2,"own_cd":22858}},{"type":"Feature","geometry":{"type":"Point","coordinates":[130.941111111,31.344444444]},"properties":{"id":222858012,"name":"前田","name_kana":"","ofc_cd":89,"sys_id":2,"sys_cam_id":"46010022","pause":0,"date_type":0,"cam_kind":2,"own_cd":22858}},{"type":"Feature","geometry":{"type":"Point","coordinates":[130.947822222,31.361388888]},"properties":{"id":222858016,"name":"高良橋水位","name_kana":"","ofc_cd":89,"sys_id":2,"sys_cam_id":"46010026","pause":0,"date_type":0,"cam_kind":2,"own_cd":22858}},{"type":"Feature","geometry":{"type":"Point","coordinates":[130.944119444,31.347080555]},"properties":{"id":222858017,"name":"高山橋水位","name_kana":"","ofc_cd":89,"sys_id":2,"sys_cam_id":"46010027","pause":0,"date_type":0,"cam_kind":2,"own_cd":22858}},{"type":"Feature","geometry":{"type":"Point","coordinates":[130.918238888,31.363147222]},"properties":{"id":222858020,"name":"宮下","name_kana":"","ofc_cd":89,"sys_id":2,"sys_cam_id":"46010030","pause":0,"date_type":0,"cam_kind":2,"own_cd":22858}}]}