{"type":"FeatureCollection","crs":{"type":"name","properties":{"name":"EPSG:4326"}},"features":[{"type":"Feature","geometry":{"type":"Point","coordinates":[136.6402222,34.5640566]},"properties":{"id":106145030,"name":"笹笛川 行部(笹笛川橋下流側)","name_kana":"ささぶえがわ ゆくべ(ささぶえがわばしかりゅうがわ)","ofc_cd":85,"sys_id":1,"sys_cam_id":"6145030","pause":0,"date_type":1,"cam_kind":4,"own_cd":6145}},{"type":"Feature","geometry":{"type":"Point","coordinates":[136.640167,34.573967]},"properties":{"id":106145048,"name":"笹笛川(根倉橋下流側)","name_kana":"ささぶえがわ(ねぐらばしかりゅうがわ)","ofc_cd":85,"sys_id":1,"sys_cam_id":"6145048","pause":0,"date_type":2,"cam_kind":4,"own_cd":6145}},{"type":"Feature","geometry":{"type":"Point","coordinates":[136.618697,34.567036]},"properties":{"id":106145080,"name":"祓川(新小藪橋下流側)","name_kana":"はらいがわ(しんこやぶばしかりゅうがわ)","ofc_cd":85,"sys_id":1,"sys_cam_id":"6145080","pause":0,"date_type":2,"cam_kind":4,"own_cd":6145}}]}