{"type":"FeatureCollection","crs":{"type":"name","properties":{"name":"EPSG:4326"}},"features":[{"type":"Feature","geometry":{"type":"Point","coordinates":[135.990630556,34.772613889]},"properties":{"id":122107002,"name":"木津川 北大河原","name_kana":"","ofc_cd":86,"sys_id":1,"sys_cam_id":"22107002","pause":0,"date_type":0,"cam_kind":4,"own_cd":22107}},{"type":"Feature","geometry":{"type":"Point","coordinates":[136.011666667,34.751944444]},"properties":{"id":219601001,"name":"ダム上流","name_kana":"","ofc_cd":76,"sys_id":2,"sys_cam_id":"19601001","pause":0,"date_type":0,"cam_kind":2,"own_cd":19601}},{"type":"Feature","geometry":{"type":"Point","coordinates":[136.011666667,34.753888889]},"properties":{"id":219601002,"name":"ダム下流","name_kana":"","ofc_cd":76,"sys_id":2,"sys_cam_id":"19601002","pause":0,"date_type":0,"cam_kind":2,"own_cd":19601}},{"type":"Feature","geometry":{"type":"Point","coordinates":[135.986688889,34.771105556]},"properties":{"id":222107022,"name":"大河原","name_kana":"","ofc_cd":86,"sys_id":2,"sys_cam_id":"22107022","pause":0,"date_type":0,"cam_kind":2,"own_cd":22107}},{"type":"Feature","geometry":{"type":"Point","coordinates":[136.010763889,34.758344444]},"properties":{"id":222107023,"name":"高山ダム下流","name_kana":"","ofc_cd":86,"sys_id":2,"sys_cam_id":"22107023","pause":0,"date_type":0,"cam_kind":2,"own_cd":22107}}]}