{"type":"FeatureCollection","crs":{"type":"name","properties":{"name":"EPSG:4326"}},"features":[{"type":"Feature","geometry":{"type":"Point","coordinates":[137.4427778,36.9330528]},"properties":{"id":221556001,"name":"下新川海岸 園家","name_kana":"","ofc_cd":84,"sys_id":2,"sys_cam_id":"16010061","pause":0,"date_type":0,"cam_kind":3,"own_cd":21556}},{"type":"Feature","geometry":{"type":"Point","coordinates":[137.4836083,36.900275]},"properties":{"id":221556020,"name":"福島","name_kana":"","ofc_cd":84,"sys_id":2,"sys_cam_id":"16010080","pause":0,"date_type":0,"cam_kind":3,"own_cd":21556}},{"type":"Feature","geometry":{"type":"Point","coordinates":[137.4369417,36.9169417]},"properties":{"id":221556021,"name":"高畠","name_kana":"","ofc_cd":84,"sys_id":2,"sys_cam_id":"16010081","pause":0,"date_type":0,"cam_kind":3,"own_cd":21556}},{"type":"Feature","geometry":{"type":"Point","coordinates":[137.5277778,36.8766639]},"properties":{"id":221556022,"name":"新屋","name_kana":"","ofc_cd":84,"sys_id":2,"sys_cam_id":"16010082","pause":0,"date_type":0,"cam_kind":3,"own_cd":21556}},{"type":"Feature","geometry":{"type":"Point","coordinates":[137.5302778,36.9597222]},"properties":{"id":221556023,"name":"下新川海岸 春日","name_kana":"","ofc_cd":84,"sys_id":2,"sys_cam_id":"16010083","pause":0,"date_type":0,"cam_kind":3,"own_cd":21556}},{"type":"Feature","geometry":{"type":"Point","coordinates":[137.5144444,36.9586083]},"properties":{"id":221556024,"name":"下新川海岸 横山","name_kana":"","ofc_cd":84,"sys_id":2,"sys_cam_id":"16010084","pause":0,"date_type":0,"cam_kind":3,"own_cd":21556}},{"type":"Feature","geometry":{"type":"Point","coordinates":[137.4822194,36.9483306]},"properties":{"id":221556025,"name":"下新川海岸 吉原","name_kana":"","ofc_cd":84,"sys_id":2,"sys_cam_id":"16010085","pause":0,"date_type":0,"cam_kind":3,"own_cd":21556}},{"type":"Feature","geometry":{"type":"Point","coordinates":[137.4513861,36.9355528]},"properties":{"id":221556026,"name":"下新川海岸 神子沢","name_kana":"","ofc_cd":84,"sys_id":2,"sys_cam_id":"16010086","pause":0,"date_type":0,"cam_kind":3,"own_cd":21556}},{"type":"Feature","geometry":{"type":"Point","coordinates":[137.4397222,36.9316639]},"properties":{"id":221556027,"name":"下新川海岸 下飯野","name_kana":"","ofc_cd":84,"sys_id":2,"sys_cam_id":"16010087","pause":0,"date_type":0,"cam_kind":3,"own_cd":21556}},{"type":"Feature","geometry":{"type":"Point","coordinates":[137.5441639,36.9613889]},"properties":{"id":221556028,"name":"下新川海岸 赤川","name_kana":"","ofc_cd":84,"sys_id":2,"sys_cam_id":"16010088","pause":0,"date_type":0,"cam_kind":3,"own_cd":21556}},{"type":"Feature","geometry":{"type":"Point","coordinates":[137.492775,36.9544444]},"properties":{"id":221556029,"name":"下新川海岸 田中","name_kana":"","ofc_cd":84,"sys_id":2,"sys_cam_id":"16010089","pause":0,"date_type":0,"cam_kind":3,"own_cd":21556}},{"type":"Feature","geometry":{"type":"Point","coordinates":[137.4588861,36.9047194]},"properties":{"id":221556030,"name":"上飯野","name_kana":"","ofc_cd":84,"sys_id":2,"sys_cam_id":"16010090","pause":0,"date_type":0,"cam_kind":3,"own_cd":21556}},{"type":"Feature","geometry":{"type":"Point","coordinates":[137.4272194,36.9241639]},"properties":{"id":221556031,"name":"芦崎","name_kana":"","ofc_cd":84,"sys_id":2,"sys_cam_id":"16010091","pause":0,"date_type":0,"cam_kind":3,"own_cd":21556}},{"type":"Feature","geometry":{"type":"Point","coordinates":[137.5086111,36.9575]},"properties":{"id":221556032,"name":"下新川海岸 八幡","name_kana":"","ofc_cd":84,"sys_id":2,"sys_cam_id":"16010092","pause":0,"date_type":0,"cam_kind":3,"own_cd":21556}},{"type":"Feature","geometry":{"type":"Point","coordinates":[137.4661083,36.9422194]},"properties":{"id":221556033,"name":"下新川海岸 木根","name_kana":"","ofc_cd":84,"sys_id":2,"sys_cam_id":"16010093","pause":0,"date_type":0,"cam_kind":3,"own_cd":21556}},{"type":"Feature","geometry":{"type":"Point","coordinates":[137.5145194,36.883425]},"properties":{"id":221556057,"name":"小摺戸","name_kana":"こすりど","ofc_cd":84,"sys_id":2,"sys_cam_id":"21556019","pause":0,"date_type":0,"cam_kind":3,"own_cd":21556}}]}