{"type":"FeatureCollection","crs":{"type":"name","properties":{"name":"EPSG:4326"}},"features":[{"type":"Feature","geometry":{"type":"Point","coordinates":[139.547579,38.307763]},"properties":{"id":103841001,"name":"早稲田","name_kana":"","ofc_cd":84,"sys_id":1,"sys_cam_id":"3841001","pause":0,"date_type":1,"cam_kind":4,"own_cd":3841}},{"type":"Feature","geometry":{"type":"Point","coordinates":[139.498656,38.257369]},"properties":{"id":103841002,"name":"宮ノ下","name_kana":"","ofc_cd":84,"sys_id":1,"sys_cam_id":"3841002","pause":0,"date_type":1,"cam_kind":4,"own_cd":3841}},{"type":"Feature","geometry":{"type":"Point","coordinates":[139.478683,38.229997]},"properties":{"id":103841003,"name":"泉町","name_kana":"","ofc_cd":84,"sys_id":1,"sys_cam_id":"3841003","pause":0,"date_type":1,"cam_kind":4,"own_cd":3841}},{"type":"Feature","geometry":{"type":"Point","coordinates":[139.49272,38.228452]},"properties":{"id":103841004,"name":"山辺里","name_kana":"","ofc_cd":84,"sys_id":1,"sys_cam_id":"3841004","pause":0,"date_type":1,"cam_kind":4,"own_cd":3841}},{"type":"Feature","geometry":{"type":"Point","coordinates":[139.46741999,38.12362778]},"properties":{"id":121528020,"name":"村上市佐々木","name_kana":"","ofc_cd":84,"sys_id":1,"sys_cam_id":"21528020","pause":0,"date_type":2,"cam_kind":4,"own_cd":21528}},{"type":"Feature","geometry":{"type":"Point","coordinates":[139.48378909,38.10986396]},"properties":{"id":121528021,"name":"村上市荒島","name_kana":"","ofc_cd":84,"sys_id":1,"sys_cam_id":"21528021","pause":0,"date_type":2,"cam_kind":4,"own_cd":21528}},{"type":"Feature","geometry":{"type":"Point","coordinates":[139.4141944,38.1529556]},"properties":{"id":221528003,"name":"塩谷","name_kana":"","ofc_cd":84,"sys_id":2,"sys_cam_id":"15010110","pause":0,"date_type":0,"cam_kind":3,"own_cd":21528}},{"type":"Feature","geometry":{"type":"Point","coordinates":[139.4612333,38.1351972]},"properties":{"id":221528004,"name":"葛籠山","name_kana":"","ofc_cd":84,"sys_id":2,"sys_cam_id":"15010111","pause":0,"date_type":0,"cam_kind":3,"own_cd":21528}},{"type":"Feature","geometry":{"type":"Point","coordinates":[139.4880778,38.1113444]},"properties":{"id":221528005,"name":"花立","name_kana":"","ofc_cd":84,"sys_id":2,"sys_cam_id":"15010112","pause":0,"date_type":0,"cam_kind":3,"own_cd":21528}}]}